mcnntunes/__init__.py
mcnntunes/app.py
mcnntunes/minimizer.py
mcnntunes/nnmodel.py
mcnntunes/report.py
mcnntunes/runcardio.py
mcnntunes/stats.py
mcnntunes/tools.py
mcnntunes/yodaio.py
mcnntunes/scripts/__init__.py
mcnntunes/scripts/mcnntemplate.py
mcnntunes/scripts/mcnntunes.py
mcnntunes/scripts/mcnntunes_buildruns.py
mcnntunes/templates/__init__.py
mcnntunes/templates/base.html
mcnntunes/templates/benchmark.html
mcnntunes/templates/config.html
mcnntunes/templates/data.html
mcnntunes/templates/index.html
mcnntunes/templates/minimization.html
mcnntunes/templates/model.html
mcnntunes/templates/optimize.html
mcnntunes/templates/raw.html
mcnntunes-0.1.0.dist-info/LICENSE
mcnntunes-0.1.0.dist-info/METADATA
mcnntunes-0.1.0.dist-info/WHEEL
mcnntunes-0.1.0.dist-info/entry_points.txt
mcnntunes-0.1.0.dist-info/top_level.txt
mcnntunes-0.1.0.dist-info/RECORD
