Metadata-Version: 2.1
Name: mcnntunes
Version: 0.1.0
Summary: MC Neural Network Tunes
Home-page: https://github.com/N3PDF/mcnntunes
Author: M. Lazzarin, S. Alioli, S. Carrazza
Author-email: 
License: UNKNOWN
Platform: UNKNOWN
Classifier: Topic :: Scientific/Engineering :: Physics
Requires-Python: >=3.6.0
Requires-Dist: cma
Requires-Dist: hyperopt
Requires-Dist: jinja2
Requires-Dist: matplotlib
Requires-Dist: pandas
Requires-Dist: pymongo
Requires-Dist: pyyaml
Requires-Dist: seaborn
Requires-Dist: tensorflow
